<?xml version="1.0" ?>

<container xmlns="http://symfony.com/schema/dic/services"
           xmlns:xsi="http://www.w3.org/2001/XMLSchema-instance"
           xsi:schemaLocation="http://symfony.com/schema/dic/services http://symfony.com/schema/dic/services/services-1.0.xsd">
    <services>
        <!--&lt;!&ndash; Queries &ndash;&gt;-->
        <!--<service id="intracto_secret_santa.query.report" class="Intracto\SecretSantaBundle\Query\ReportQuery">-->
            <!--<argument type="service" id="intracto_secret_santa.query.party_report"/>-->
            <!--<argument type="service" id="intracto_secret_santa.query.participant_report"/>-->
            <!--<argument type="service" id="intracto_secret_santa.query.ip_report"/>-->
            <!--<argument type="service" id="intracto_secret_santa.query.wishlist_report"/>-->
        <!--</service>-->
        <!--<service id="intracto_secret_santa.query.party_report" class="Intracto\SecretSantaBundle\Query\PartyReportQuery">-->
            <!--<argument type="service" id="database_connection"/>-->
            <!--<argument type="service" id="intracto_secret_santa.query.featured_years_report"/>-->
        <!--</service>-->
        <!--<service id="intracto_secret_santa.query.participant_report" class="Intracto\SecretSantaBundle\Query\ParticipantReportQuery">-->
            <!--<argument type="service" id="database_connection"/>-->
            <!--<argument type="service" id="router"/>-->
            <!--<argument type="service" id="intracto_secret_santa.query.party_report"/>-->
            <!--<argument type="service" id="intracto_secret_santa.query.featured_years_report"/>-->
        <!--</service>-->
        <!--<service id="intracto_secret_santa.query.ip_report" class="Intracto\SecretSantaBundle\Query\IpReportQuery">-->
            <!--<argument type="service" id="database_connection"/>-->
        <!--</service>-->
        <!--<service id="intracto_secret_santa.query.wishlist_report" class="Intracto\SecretSantaBundle\Query\WishlistReportQuery">-->
            <!--<argument type="service" id="database_connection"/>-->
            <!--<argument type="service" id="intracto_secret_santa.query.participant_report"/>-->
        <!--</service>-->
        <!--<service id="intracto_secret_santa.query.featured_years_report" class="Intracto\SecretSantaBundle\Query\FeaturedYearsQuery">-->
            <!--<argument type="service" id="database_connection"/>-->
        <!--</service>-->
        <!--<service id="intracto_secret_santa.query.google_analytics" class="Intracto\SecretSantaBundle\Query\GoogleAnalyticsQuery">-->
            <!--<argument>%ga_view_id%</argument>-->
            <!--<argument>%kernel.root_dir%/config/client_secrets.json</argument>-->
        <!--</service>-->
        <!--<service id="intracto_secret_santa.query.season_comparison_report" class="Intracto\SecretSantaBundle\Query\SeasonComparisonReportQuery">-->
            <!--<argument type="service" id="intracto_secret_santa.query.party_report"/>-->
            <!--<argument type="service" id="intracto_secret_santa.query.participant_report"/>-->
            <!--<argument type="service" id="intracto_secret_santa.query.wishlist_report"/>-->
        <!--</service>-->
        <!--<service id="intracto_secret_santa.query.participant_mail" class="Intracto\SecretSantaBundle\Query\ParticipantMailQuery">-->
            <!--<argument type="service" id="doctrine.orm.entity_manager"/>-->
        <!--</service>-->
        <!--<service id="intracto_secret_santa.query.wishlist_mail" class="Intracto\SecretSantaBundle\Query\WishlistMailQuery">-->
            <!--<argument type="service" id="database_connection"/>-->
        <!--</service>-->
        <!--<service id="intracto_secret_santa.query.bounce" class="Intracto\SecretSantaBundle\Query\BounceQuery">-->
            <!--<argument type="service" id="database_connection"/>-->
        <!--</service>-->

        <!-- Repositories -->
        <service id="intracto_secret_santa.repository.party" class="Doctrine\ORM\EntityRepository">
            <factory service="doctrine.orm.entity_manager" method="getRepository" />
            <argument>IntractoSecretSantaBundle:Party</argument>
        </service>
        <service id="intracto_secret_santa.repository.participant" class="Doctrine\ORM\EntityRepository">
            <factory service="doctrine.orm.entity_manager" method="getRepository" />
            <argument>IntractoSecretSantaBundle:Participant</argument>
        </service>

        <!--&lt;!&ndash; Services &ndash;&gt;-->
        <!--<service id="intracto_secret_santa.service.participant" class="Intracto\SecretSantaBundle\Service\ParticipantService">-->
            <!--<argument type="service" id="doctrine.orm.entity_manager" />-->
            <!--<argument type="service" id="intracto_secret_santa.service.participant_shuffler" />-->
            <!--<argument type="service" id="validator"/>-->
        <!--</service>-->
        <!--<service id="intracto_secret_santa.service.party" class="Intracto\SecretSantaBundle\Service\PartyService">-->
            <!--<argument type="service" id="intracto_secret_santa.mailer" />-->
            <!--<argument type="service" id="doctrine.orm.entity_manager" />-->
            <!--<argument type="service" id="intracto_secret_santa.service.participant" />-->
        <!--</service>-->
        <!--<service id="intracto_secret_santa.service.export" class="Intracto\SecretSantaBundle\Service\ExportService" />-->
        <!--<service id="intracto_secret_santa.service.participant_shuffler" class="Intracto\SecretSantaBundle\Service\ParticipantShuffler" />-->
        <!--<service id="intracto_secret_santa.service.unsubscribe" class="Intracto\SecretSantaBundle\Service\UnsubscribeService" >-->
            <!--<argument type="service" id="doctrine.orm.entity_manager"/>-->
            <!--<argument type="service" id="router"/>-->
        <!--</service>-->

        <!--&lt;!&ndash; Twig &ndash;&gt;-->
        <!--<service id="intracto_secret_santa.twig.extension.form" class="Intracto\SecretSantaBundle\Twig\Extension\FormExtension">-->
            <!--<argument type="service" id="twig.form.renderer" />-->
            <!--<tag name="twig.extension" />-->
        <!--</service>-->
        <!--<service id="intracto_secret_santa.twig.linkify_extension" class="Intracto\SecretSantaBundle\Twig\LinkifyExtension">-->
            <!--<tag name="twig.extension" />-->
        <!--</service>-->
        <!--<service id="intracto_secret_santa.twig.mailstatus_extension" class="Intracto\SecretSantaBundle\Twig\MailStatusExtension">-->
            <!--<tag name="twig.extension" />-->
            <!--<argument type="service" id="translator"/>-->
        <!--</service>-->

        <!--&lt;!&ndash; Form &ndash;&gt;-->
        <!--<service id="intracto_secret_santa.form.extension.jquery_date_type" class="Intracto\SecretSantaBundle\Form\Extension\DateTypeExtension">-->
            <!--<tag name="form.type_extension" extended_type="Symfony\Component\Form\Extension\Core\Type\DateType" />-->
        <!--</service>-->

        <!--&lt;!&ndash; Form handlers &ndash;&gt;-->
        <!--<service id="intracto_secret_santa.form_handler.party" class="Intracto\SecretSantaBundle\Form\Handler\PartyFormHandler">-->
            <!--<argument type="service" id="doctrine.orm.default_entity_manager" />-->
            <!--<argument type="service" id="intracto_secret_santa.mailer" />-->
        <!--</service>-->
        <!--<service id="intracto_secret_santa.form_handler.unsubcribe" class="Intracto\SecretSantaBundle\Form\Handler\UnsubscribeFormHandler">-->
            <!--<argument type="service" id="translator" />-->
            <!--<argument type="service" id="session" />-->
            <!--<argument type="service" id="intracto_secret_santa.service.unsubscribe" />-->
        <!--</service>-->
        <!--<service id="intracto_secret_santa.form_handler.forgot_url" class="Intracto\SecretSantaBundle\Form\Handler\ForgotUrlFormHandler">-->
            <!--<argument type="service" id="translator" />-->
            <!--<argument type="service" id="session" />-->
            <!--<argument type="service" id="intracto_secret_santa.mailer" />-->
        <!--</service>-->
        <!--<service id="intracto_secret_santa.form_handler.reuse" class="Intracto\SecretSantaBundle\Form\Handler\ReuseFormHandler">-->
            <!--<argument type="service" id="translator" />-->
            <!--<argument type="service" id="session" />-->
            <!--<argument type="service" id="intracto_secret_santa.mailer" />-->
        <!--</service>-->
        <!--<service id="intract_secret_santa.form_handler.add_participant" class="Intracto\SecretSantaBundle\Form\Handler\AddParticipantFormHandler">-->
            <!--<argument type="service" id="translator"/>-->
            <!--<argument type="service" id="session"/>-->
            <!--<argument type="service" id="doctrine.orm.entity_manager"/>-->
            <!--<argument type="service" id="intracto_secret_santa.mailer"/>-->
        <!--</service>-->
        <!--<service id="intracto_secret_santa.form_handler.wishlist" class="Intracto\SecretSantaBundle\Form\Handler\WishlistFormHandler">-->
            <!--<argument type="service" id="doctrine.orm.entity_manager"/>-->
        <!--</service>-->
        <!--<service id="intract_secret_santa.form_handler.send_message" class="Intracto\SecretSantaBundle\Form\Handler\SendMessageFormHandler">-->
            <!--<argument type="service" id="session"/>-->
            <!--<argument type="service" id="translator"/>-->
            <!--<argument type="service" id="doctrine.orm.default_entity_manager"/>-->
            <!--<argument type="service" id="intracto_secret_santa.mailer"/>-->
        <!--</service>-->

        <!--&lt;!&ndash; Validators &ndash;&gt;-->
        <!--<service id="intracto_secret_santa.validator.participant_has_valid_excludes" class="Intracto\SecretSantaBundle\Validator\ParticipantHasValidExcludesValidator">-->
            <!--<tag name="validator.constraint_validator" alias="intracto_secret_santa.validator.participant_has_valid_excludes" />-->
        <!--</service>-->
        <!--<service id="intracto_secret_santa.validator.party_has_valid_excludes" class="Intracto\SecretSantaBundle\Validator\PartyHasValidExcludesValidator">-->
            <!--<argument type="service" id="intracto_secret_santa.service.participant_shuffler" />-->
            <!--<tag name="validator.constraint_validator" alias="intracto_secret_santa.validator.party_has_valid_excludes" />-->
        <!--</service>-->
        <!--<service id="intracto_secret_santa.validator.participant_is_not_blacklisted" class="Intracto\SecretSantaBundle\Validator\ParticipantIsNotBlacklistedValidator">-->
            <!--<argument type="service" id="doctrine.orm.default_entity_manager" />-->
            <!--<tag name="validator.constraint_validator" alias="intracto_secret_santa.validator.participant_is_not_blacklisted" />-->
        <!--</service>-->

        <!--&lt;!&ndash; Mailer &ndash;&gt;-->
        <!--<service id="intracto_secret_santa.mailer" class="Intracto\SecretSantaBundle\Mailer\MailerService">-->
            <!--<argument type="service" id="mailer"/>-->
            <!--<argument type="service" id="doctrine.orm.entity_manager"/>-->
            <!--<argument type="service" id="templating"/>-->
            <!--<argument type="service" id="translator"/>-->
            <!--<argument type="service" id="router"/>-->
            <!--<argument type="service" id="intracto_secret_santa.service.unsubscribe"/>-->
            <!--<argument>%noreply_email%</argument>-->
        <!--</service>-->
    </services>
</container>
